gitea/__init__.py
gitea/api_client.py
gitea/configuration.py
gitea/rest.py
gitea/api/__init__.py
gitea/api/activitypub_api.py
gitea/api/admin_api.py
gitea/api/issue_api.py
gitea/api/miscellaneous_api.py
gitea/api/notification_api.py
gitea/api/organization_api.py
gitea/api/package_api.py
gitea/api/repository_api.py
gitea/api/settings_api.py
gitea/api/user_api.py
gitea/models/__init__.py
gitea/models/access_token.py
gitea/models/action_variable.py
gitea/models/activity.py
gitea/models/activity_pub.py
gitea/models/add_collaborator_option.py
gitea/models/add_time_option.py
gitea/models/annotated_tag.py
gitea/models/annotated_tag_object.py
gitea/models/api_error.py
gitea/models/attachment.py
gitea/models/badge.py
gitea/models/branch.py
gitea/models/branch_protection.py
gitea/models/change_file_operation.py
gitea/models/change_files_options.py
gitea/models/changed_file.py
gitea/models/combined_status.py
gitea/models/comment.py
gitea/models/commit.py
gitea/models/commit_affected_files.py
gitea/models/commit_date_options.py
gitea/models/commit_meta.py
gitea/models/commit_stats.py
gitea/models/commit_status.py
gitea/models/commit_status_state.py
gitea/models/commit_user.py
gitea/models/compare.py
gitea/models/contents_response.py
gitea/models/create_access_token_option.py
gitea/models/create_branch_protection_option.py
gitea/models/create_branch_repo_option.py
gitea/models/create_email_option.py
gitea/models/create_file_options.py
gitea/models/create_fork_option.py
gitea/models/create_gpg_key_option.py
gitea/models/create_hook_option.py
gitea/models/create_hook_option_config.py
gitea/models/create_issue_comment_option.py
gitea/models/create_issue_option.py
gitea/models/create_key_option.py
gitea/models/create_label_option.py
gitea/models/create_milestone_option.py
gitea/models/create_o_auth2_application_options.py
gitea/models/create_or_update_secret_option.py
gitea/models/create_org_option.py
gitea/models/create_pull_request_option.py
gitea-1.0.0.dist-info/METADATA
gitea-1.0.0.dist-info/WHEEL
gitea-1.0.0.dist-info/top_level.txt
gitea-1.0.0.dist-info/RECORD
