Metadata-Version: 2.1
Name: gitea
Version: 1.0.0
Summary: Gitea API
Home-page: 
Author-email: 
Keywords: Swagger,Gitea API
Requires-Dist: urllib3>=1.15
Requires-Dist: six>=1.10
Requires-Dist: certifi
Requires-Dist: python-dateutil
